{
    "people" : [
        {
            "id": 1,
            "gender" : "male",
            "bag" : true,
            "hat" : false, 
            "upper_color" : "red",
            "lower_color" : "blue",
            "roi1_passages" : 1,
            "roi1_persistence_time" : 32,
            "roi2_passages" : 2,
            "roi2_persistence_time" : 45
        }, 
        {
            "id" : 2,
            "gender" : "female",
            "bag" : false,
            "hat" : true,
            "upper_color" : "black",
            "lower_color" : "white",
            "roi1_passages" : 0,
            "roi1_persistence_time" : 0,
            "roi2_passages" : 1,
            "roi2_persistence_time" : 12
        },
        {
            "id": 3,
            "gender": "male",
            "bag": true,
            "hat": true,
            "upper_color": "green",
            "lower_color": "brown",
            "roi1_passages": 3,
            "roi1_persistence_time": 20,
            "roi2_passages": 1,
            "roi2_persistence_time": 18
        },
        {
            "id": 4,
            "gender": "female",
            "bag": true,
            "hat": false,
            "upper_color": "blue",
            "lower_color": "pink",
            "roi1_passages": 2,
            "roi1_persistence_time": 15,
            "roi2_passages": 0,
            "roi2_persistence_time": 0
        },
        {
            "id": 5,
            "gender": "male",
            "bag": true,
            "hat": false,
            "upper_color": "red",
            "lower_color": "blue",
            "roi1_passages": 1,
            "roi1_persistence_time": 32,
            "roi2_passages": 2,
            "roi2_persistence_time": 45
        },
        {
            "id": 6,
            "gender": "female",
            "bag": false,
            "hat": true,
            "upper_color": "black",
            "lower_color": "white",
            "roi1_passages": 0,
            "roi1_persistence_time": 0,
            "roi2_passages": 1,
            "roi2_persistence_time": 12
        },
        {
            "id": 7,
            "gender": "male",
            "bag": true,
            "hat": true,
            "upper_color": "green",
            "lower_color": "brown",
            "roi1_passages": 3,
            "roi1_persistence_time": 20,
            "roi2_passages": 1,
            "roi2_persistence_time": 18
        },
        {
            "id": 8,
            "gender": "female",
            "bag": true,
            "hat": false,
            "upper_color": "blue",
            "lower_color": "pink",
            "roi1_passages": 2,
            "roi1_persistence_time": 15,
            "roi2_passages": 0,
            "roi2_persistence_time": 0
        },
        {
            "id": 9,
            "gender": "male",
            "bag": false,
            "hat": true,
            "upper_color": "yellow",
            "lower_color": "gray",
            "roi1_passages": 1,
            "roi1_persistence_time": 10,
            "roi2_passages": 2,
            "roi2_persistence_time": 25
        },
        {
            "id": 10,
            "gender": "female",
            "bag": true,
            "hat": true,
            "upper_color": "purple",
            "lower_color": "orange",
            "roi1_passages": 4,
            "roi1_persistence_time": 40,
            "roi2_passages": 3,
            "roi2_persistence_time": 30
        }, 
        {
            "id": 11,
            "gender": "male",
            "bag": true,
            "hat": false,
            "upper_color": "red",
            "lower_color": "blue",
            "roi1_passages": 1,
            "roi1_persistence_time": 32,
            "roi2_passages": 2,
            "roi2_persistence_time": 45
        },
        {
            "id": 12,
            "gender": "female",
            "bag": false,
            "hat": true,
            "upper_color": "black",
            "lower_color": "white",
            "roi1_passages": 0,
            "roi1_persistence_time": 0,
            "roi2_passages": 1,
            "roi2_persistence_time": 12
        },
        {
            "id": 13,
            "gender": "male",
            "bag": true,
            "hat": true,
            "upper_color": "green",
            "lower_color": "brown",
            "roi1_passages": 3,
            "roi1_persistence_time": 20,
            "roi2_passages": 1,
            "roi2_persistence_time": 18
        },
        {
            "id": 14,
            "gender": "female",
            "bag": true,
            "hat": false,
            "upper_color": "blue",
            "lower_color": "pink",
            "roi1_passages": 2,
            "roi1_persistence_time": 15,
            "roi2_passages": 0,
            "roi2_persistence_time": 0
        },
        {
            "id": 15,
            "gender": "male",
            "bag": false,
            "hat": true,
            "upper_color": "yellow",
            "lower_color": "gray",
            "roi1_passages": 1,
            "roi1_persistence_time": 10,
            "roi2_passages": 2,
            "roi2_persistence_time": 25
        },
        {
            "id": 16,
            "gender": "female",
            "bag": true,
            "hat": true,
            "upper_color": "purple",
            "lower_color": "orange",
            "roi1_passages": 4,
            "roi1_persistence_time": 40,
            "roi2_passages": 3,
            "roi2_persistence_time": 30
        },
        {
            "id": 17,
            "gender": "male",
            "bag": true,
            "hat": false,
            "upper_color": "red",
            "lower_color": "blue",
            "roi1_passages": 1,
            "roi1_persistence_time": 32,
            "roi2_passages": 2,
            "roi2_persistence_time": 45
        },
        {
            "id": 18,
            "gender": "female",
            "bag": false,
            "hat": true,
            "upper_color": "black",
            "lower_color": "white",
            "roi1_passages": 0,
            "roi1_persistence_time": 0,
            "roi2_passages": 1,
            "roi2_persistence_time": 12
        },
        {
            "id": 19,
            "gender": "male",
            "bag": true,
            "hat": true,
            "upper_color": "green",
            "lower_color": "brown",
            "roi1_passages": 3,
            "roi1_persistence_time": 20,
            "roi2_passages": 1,
            "roi2_persistence_time": 18
        },
        {
            "id": 20,
            "gender": "female",
            "bag": true,
            "hat": false,
            "upper_color": "blue",
            "lower_color": "pink",
            "roi1_passages": 2,
            "roi1_persistence_time": 15,
            "roi2_passages": 0,
            "roi2_persistence_time": 0
        },
        {
            "id": 21,
            "gender": "male",
            "bag": false,
            "hat": true,
            "upper_color": "yellow",
            "lower_color": "gray",
            "roi1_passages": 1,
            "roi1_persistence_time": 10,
            "roi2_passages": 2,
            "roi2_persistence_time": 25
        },
        {
            "id": 22,
            "gender": "female",
            "bag": true,
            "hat": true,
            "upper_color": "purple",
            "lower_color": "orange",
            "roi1_passages": 4,
            "roi1_persistence_time": 40,
            "roi2_passages": 3,
            "roi2_persistence_time": 30
        },
        {
            "id": 23,
            "gender": "male",
            "bag": false,
            "hat": false,
            "upper_color": "orange",
            "lower_color": "black",
            "roi1_passages": 0,
            "roi1_persistence_time": 0,
            "roi2_passages": 1,
            "roi2_persistence_time": 12
        },
        {
            "id": 24,
            "gender": "female",
            "bag": true,
            "hat": false,
            "upper_color": "brown",
            "lower_color": "black",
            "roi1_passages": 2,
            "roi1_persistence_time": 18,
            "roi2_passages": 4,
            "roi2_persistence_time": 35
        },
        {
            "id": 25,
            "gender": "male",
            "bag": true,
            "hat": true,
            "upper_color": "orange",
            "lower_color": "gray",
            "roi1_passages": 1,
            "roi1_persistence_time": 25,
            "roi2_passages": 3,
            "roi2_persistence_time": 22
        },
        {
            "id": 26,
            "gender": "female",
            "bag": false,
            "hat": true,
            "upper_color": "blue",
            "lower_color": "pink",
            "roi1_passages": 0,
            "roi1_persistence_time": 0,
            "roi2_passages": 2,
            "roi2_persistence_time": 15
        },
        {
            "id": 27,
            "gender": "male",
            "bag": true,
            "hat": false,
            "upper_color": "red",
            "lower_color": "yellow",
            "roi1_passages": 0,
            "roi1_persistence_time": 0,
            "roi2_passages": 2,
            "roi2_persistence_time": 15
        },
        {
            "id": 28,
            "gender": "male",
            "bag": true,
            "hat": false,
            "upper_color": "gray",
            "lower_color": "yellow",
            "roi1_passages": 7,
            "roi1_persistence_time": 8,
            "roi2_passages": 2,
            "roi2_persistence_time": 15
        }
    ]
}